docs/build/html/_static/conf.py
docs/source/conf.py
rswiki_wrapper/__init__.py
rswiki_wrapper/osrs.py
rswiki_wrapper/wiki.py
tests/__init__.py
tests/test_osrs.py
tests/test_wiki.py
venv/Lib/site-packages/_virtualenv.py
venv/Lib/site-packages/imagesize.py
venv/Lib/site-packages/py.py
venv/Lib/site-packages/six.py
venv/Lib/site-packages/_distutils_hack/__init__.py
venv/Lib/site-packages/_distutils_hack/override.py
venv/Lib/site-packages/_pytest/__init__.py
venv/Lib/site-packages/_pytest/_argcomplete.py
venv/Lib/site-packages/_pytest/_version.py
venv/Lib/site-packages/_pytest/cacheprovider.py
venv/Lib/site-packages/_pytest/capture.py
venv/Lib/site-packages/_pytest/compat.py
venv/Lib/site-packages/_pytest/debugging.py
venv/Lib/site-packages/_pytest/deprecated.py
venv/Lib/site-packages/_pytest/doctest.py
venv/Lib/site-packages/_pytest/faulthandler.py
venv/Lib/site-packages/_pytest/fixtures.py
venv/Lib/site-packages/_pytest/freeze_support.py
venv/Lib/site-packages/_pytest/helpconfig.py
venv/Lib/site-packages/_pytest/hookspec.py
venv/Lib/site-packages/_pytest/junitxml.py
venv/Lib/site-packages/_pytest/legacypath.py
venv/Lib/site-packages/_pytest/logging.py
venv/Lib/site-packages/_pytest/main.py
venv/Lib/site-packages/_pytest/monkeypatch.py
venv/Lib/site-packages/_pytest/nodes.py
venv/Lib/site-packages/_pytest/nose.py
venv/Lib/site-packages/_pytest/outcomes.py
venv/Lib/site-packages/_pytest/pastebin.py
venv/Lib/site-packages/_pytest/pathlib.py
venv/Lib/site-packages/_pytest/pytester.py
venv/Lib/site-packages/_pytest/pytester_assertions.py
venv/Lib/site-packages/_pytest/python.py
venv/Lib/site-packages/_pytest/python_api.py
venv/Lib/site-packages/_pytest/python_path.py
venv/Lib/site-packages/_pytest/recwarn.py
venv/Lib/site-packages/_pytest/reports.py
venv/Lib/site-packages/_pytest/runner.py
venv/Lib/site-packages/_pytest/scope.py
venv/Lib/site-packages/_pytest/setuponly.py
venv/Lib/site-packages/_pytest/setupplan.py
venv/Lib/site-packages/_pytest/skipping.py
rswiki_wrapper-0.0.6.dist-info/LICENSE
rswiki_wrapper-0.0.6.dist-info/METADATA
rswiki_wrapper-0.0.6.dist-info/WHEEL
rswiki_wrapper-0.0.6.dist-info/top_level.txt
rswiki_wrapper-0.0.6.dist-info/RECORD
