Metadata-Version: 2.1
Name: rswiki-wrapper
Version: 0.0.6
Summary: RS Wiki API Wrapper
License: MIT License
Keywords: rswiki,runescape,osrs
Classifier: Development Status :: 3 - Alpha
Classifier: License :: OSI Approved :: MIT License
Classifier: Programming Language :: Python :: 3
Requires-Python: >=3.9
License-File: LICENSE
Requires-Dist: requests
